sbis/__init__.py
sbis_api_client-0.0.3.dist-info/METADATA
sbis_api_client-0.0.3.dist-info/WHEEL
sbis_api_client-0.0.3.dist-info/top_level.txt
sbis_api_client-0.0.3.dist-info/RECORD
