Metadata-Version: 2.1
Name: sbis-api-client
Version: 0.0.3
Summary: Python библиотека для работы с API СБИС
Home-page: https://github.com/juzyram/sbis-api-client
Author: juzyram
Project-URL: GitHub, https://github.com/juzyram
Keywords: files speedfiles
Classifier: Programming Language :: Python :: 3
Classifier: License :: OSI Approved :: MIT License
Classifier: Operating System :: OS Independent
Requires-Python: >=3.6
Requires-Dist: requests >=2.32.3
